streamydeck/__init__.py
streamydeck/streamydeck.py
streamydeck-1.1.0.dist-info/METADATA
streamydeck-1.1.0.dist-info/WHEEL
streamydeck-1.1.0.dist-info/top_level.txt
streamydeck-1.1.0.dist-info/RECORD
