Metadata-Version: 2.1
Name: streamydeck
Version: 1.1.0
Summary: Streamy Deck
Author: Philippe Remy
License: MIT
Requires-Dist: streamdeck
Requires-Dist: pillow
